undockit/__init__.py
undockit/__main__.py
undockit/__version__.py
undockit/args.py
undockit/deploy.py
undockit/install.py
undockit/main.py
undockit/backend/__init__.py
undockit/backend/base.py
undockit/backend/podman.py
undockit-0.0.5.dist-info/entry_points.txt
undockit-0.0.5.dist-info/licenses/LICENSE.md
undockit-0.0.5.dist-info/WHEEL
undockit-0.0.5.dist-info/METADATA
undockit-0.0.5.dist-info/RECORD
