Metadata-Version: 2.4
Name: undockit
Version: 0.0.5
Summary: run dockerfiles as commands
Author-email: Gareth Davidson <gaz@bitplane.net>
Requires-Python: >=3.10
License-File: LICENSE.md
Requires-Dist: pre-commit ; extra == "dev"
Requires-Dist: pytest ; extra == "dev"
Requires-Dist: coverage ; extra == "dev"
Requires-Dist: pytest-cov ; extra == "dev"
Requires-Dist: build ; extra == "dev"
Requires-Dist: twine ; extra == "dev"
Requires-Dist: ruff ; extra == "dev"
Requires-Dist: pydoc-markdown ; extra == "dev"
Project-URL: Bug Tracker, https://github.com/bitplane/undockit/issues
Project-URL: Homepage, https://github.com/bitplane/undockit
Project-URL: Repository, https://github.com/bitplane/undockit
Provides-Extra: dev
